oplus/__init__.py
oplus/configuration.py
oplus/eio.py
oplus/epw.py
oplus/err.py
oplus/idd.py
oplus/idf.py
oplus/mtd.py
oplus/output_table.py
oplus/simulation.py
oplus/standard_output.py
oplus/summary_table.py
oplus/util.py
oplus/version.py
oplus/tests/__init__.py
oplus/tests/check_idf_in_out.py
oplus/tests/check_many_simulations.py
oplus/tests/test_eio.py
oplus/tests/test_epw.py
oplus/tests/test_err.py
oplus/tests/test_idd.py
oplus/tests/test_simulate.py
oplus/tests/test_summary_table.py
oplus/tests/excluded/__init__.py
oplus/tests/excluded/test_idf.py
oplus/tests/excluded/test_idf_manager.py
oplus/tests/excluded/test_standard_output.py
oplus/tests/resources/epw/USA_CA_San.Francisco.Intl.AP.724940_TMY3.csv
oplus-5.1.3.dist-info/DESCRIPTION.rst
oplus-5.1.3.dist-info/METADATA
oplus-5.1.3.dist-info/RECORD
oplus-5.1.3.dist-info/WHEEL
oplus-5.1.3.dist-info/metadata.json
oplus-5.1.3.dist-info/top_level.txt
