Metadata-Version: 2.0
Name: oplus
Version: 5.1.3
Summary: UNKNOWN
Home-page: https://github.com/Openergy/oplus
Author: Geoffroy d'Estaintot
Author-email: geoffroy.destaintot@openergy.fr
License: UNKNOWN
Platform: UNKNOWN
Classifier: Programming Language :: Python
Classifier: Development Status :: 5 - Production/Stable
Classifier: Intended Audience :: Science/Research
Classifier: Natural Language :: French
Classifier: Operating System :: POSIX :: Linux
Classifier: Programming Language :: Python :: 3.6
Classifier: Topic :: Scientific/Engineering :: Physics
Requires-Dist: nose (>=1.3.7,<4.1)
Requires-Dist: nose-exclude (<1.0.0,>=0.4.1)
Requires-Dist: pandas (>=0.16.2,<1.0.0)
Requires-Dist: plotly (<2.0.0,>=1.9.6)
